README.txt
setup.py
sitecopy2sitedeploy.py
sitedeploy.py
sitelib.py
sitedeploy.egg-info/PKG-INFO
sitedeploy.egg-info/SOURCES.txt
sitedeploy.egg-info/dependency_links.txt
sitedeploy.egg-info/top_level.txt