Metadata-Version: 1.0
Name: sitedeploy
Version: 1.0
Summary: site deployment
Home-page: http://www.smallbulb.net
Author: David Siroky
Author-email: siroky@dasir.cz
License: MIT License
Keywords: site,deploy,synchronize,ftp,ssh
Platform: UNKNOWN
Classifier: Development Status :: 5 - Production/Stable
Classifier: Intended Audience :: Developers
Classifier: Intended Audience :: System Administrators
Classifier: License :: OSI Approved :: MIT License
Classifier: Topic :: System :: Networking
Classifier: Topic :: Internet :: WWW/HTTP :: Site Management
Classifier: Topic :: Software Development
Classifier: Topic :: Utilities
